im333rsa/__init__.py
im333rsa/im333rsa.py
im333rsa-1001.dist-info/METADATA
im333rsa-1001.dist-info/WHEEL
im333rsa-1001.dist-info/entry_points.txt
im333rsa-1001.dist-info/top_level.txt
im333rsa-1001.dist-info/RECORD
