Metadata-Version: 2.4
Name: im333rsa
Version: 1001
Summary: High-security encryption tool using RSA-4096 and AES-256 with anti-debug and self-destruct.
Author: I M A D
Author-email: imad213.official@gmail.com
Classifier: Programming Language :: Python :: 3
Classifier: License :: OSI Approved :: MIT License
Classifier: Operating System :: OS Independent
Classifier: Topic :: Security :: Cryptography
Requires-Python: >=3.6
Requires-Dist: pycryptodome>=3.19.0
Requires-Dist: pyfiglet>=0.8.post1
Requires-Dist: psutil
Dynamic: author
Dynamic: author-email
Dynamic: classifier
Dynamic: description
Dynamic: description-content-type
Dynamic: requires-dist
Dynamic: requires-python
Dynamic: summary
